setup.cfg
setup.py
django_searchview.egg-info/PKG-INFO
django_searchview.egg-info/SOURCES.txt
django_searchview.egg-info/dependency_links.txt
django_searchview.egg-info/top_level.txt
searchview/__init__.py
searchview/forms.py
searchview/views.py