Metadata-Version: 1.0
Name: django-searchview
Version: 0.0.1
Summary: Generic search view
Home-page: http://github.com/odoku/django-searchview
Author: odoku
Author-email: contact@odoku.net
License: UNKNOWN
Keywords: django,view,form,search
Platform: UNKNOWN
